spellcaster.py
spellcaster-1.0.0.dist-info/LICENSE
spellcaster-1.0.0.dist-info/METADATA
spellcaster-1.0.0.dist-info/WHEEL
spellcaster-1.0.0.dist-info/top_level.txt
spellcaster-1.0.0.dist-info/RECORD
