Metadata-Version: 2.1
Name: spellcaster
Version: 1.0.0
Summary: Take control of Python with ease with the legendary Spellcaster!
Home-page: https://bytewizarddocs.github.io/spellcaster
Author: Omer Drkić
Author-email: omerdrkic2501@gmail.com
Maintainer: Byte Wraith Technologies
License: Boost Software License 1.0
Classifier: Development Status :: 5 - Production/Stable
Classifier: Environment :: Console
Classifier: Framework :: Jupyter
Classifier: Intended Audience :: Developers
Classifier: License :: OSI Approved :: Boost Software License 1.0 (BSL-1.0)
Classifier: Natural Language :: English
Classifier: Operating System :: Microsoft
Classifier: Programming Language :: Python :: 3.10
Classifier: Programming Language :: Python :: 3.11
Classifier: Programming Language :: Python :: 3.12
Classifier: Topic :: Software Development :: Interpreters
Classifier: Topic :: Software Development :: Libraries
Classifier: Typing :: Typed
Requires-Python: >=3.11
License-File: LICENSE
Requires-Dist: keyboard
